hydra_plugins/hydra_nevergrad_sweeper/__init__.py
hydra_plugins/hydra_nevergrad_sweeper/_impl.py
hydra_plugins/hydra_nevergrad_sweeper/config.py
hydra_plugins/hydra_nevergrad_sweeper/nevergrad_sweeper.py
hydra_nevergrad_sweeper-1.2.0.dist-info/METADATA
hydra_nevergrad_sweeper-1.2.0.dist-info/WHEEL
hydra_nevergrad_sweeper-1.2.0.dist-info/top_level.txt
hydra_nevergrad_sweeper-1.2.0.dist-info/RECORD
