Metadata-Version: 2.1
Name: hydra-nevergrad-sweeper
Version: 1.2.0
Summary: Hydra Nevergrad Sweeper plugin
Home-page: https://github.com/facebookresearch/hydra/
Author: Jeremy Rapin, Omry Yadan, Jieru Hu
Author-email: jrapin@fb.com, omry@fb.com, jieru@fb.com
License: UNKNOWN
Platform: UNKNOWN
Classifier: License :: OSI Approved :: MIT License
Classifier: Programming Language :: Python :: 3.6
Classifier: Programming Language :: Python :: 3.7
Classifier: Programming Language :: Python :: 3.8
Classifier: Programming Language :: Python :: 3.9
Classifier: Operating System :: OS Independent
Classifier: Development Status :: 4 - Beta
Requires-Dist: hydra-core (>=1.1.0.dev7)
Requires-Dist: nevergrad (>=0.4.3.post9)
Requires-Dist: cma (==3.0.3)
Requires-Dist: numpy (<1.20.0)
